bcentral/__init__.py
bcentral/client.py
bcentral-0.1.1.dist-info/WHEEL
bcentral-0.1.1.dist-info/METADATA
bcentral-0.1.1.dist-info/RECORD
