Metadata-Version: 2.1
Name: bcentral
Version: 0.1.1
Summary: Chilean Central Bank API Client
Author: Héctor Urbina
Author-email: hurbinas@gmail.com
Requires-Python: >=3.6,<4.0
Classifier: Programming Language :: Python :: 3
Classifier: Programming Language :: Python :: 3.6
Classifier: Programming Language :: Python :: 3.7
Classifier: Programming Language :: Python :: 3.8
Classifier: Programming Language :: Python :: 3.9
Requires-Dist: requests (>=2.26.0,<3.0.0)
